ansiwrap/__init__.py
ansiwrap/ansistate.py
ansiwrap/core.py
ansiwrap-0.8.3.dist-info/DESCRIPTION.rst
ansiwrap-0.8.3.dist-info/METADATA
ansiwrap-0.8.3.dist-info/RECORD
ansiwrap-0.8.3.dist-info/WHEEL
ansiwrap-0.8.3.dist-info/metadata.json
ansiwrap-0.8.3.dist-info/top_level.txt
